README.md
setup.py
mancho/__init__.py
mancho/__main__.py
mancho/app.py
mancho/audio.py
mancho/main.glade
mancho/wave_display.py
mancho.egg-info/PKG-INFO
mancho.egg-info/SOURCES.txt
mancho.egg-info/dependency_links.txt
mancho.egg-info/not-zip-safe
mancho.egg-info/requires.txt
mancho.egg-info/top_level.txt