Metadata-Version: 2.1
Name: mancho
Version: 0.0.3
Summary: A musical transcription tool
Home-page: https://git.arkocal.rocks/arkocal/transcriber
Author: Ali Rasim Kocal
Author-email: arkocal@posteo.net
License: UNKNOWN
Keywords: music musical transcription tool
Platform: UNKNOWN
Classifier: Programming Language :: Python :: 3
Classifier: License :: OSI Approved :: GNU Affero General Public License v3
Classifier: Operating System :: OS Independent
Requires-Python: >=3.6
